LICENSE
yolov3_tf/__init__.py
yolov3_tf/dataset.py
yolov3_tf/evaluate.py
yolov3_tf/faker.py
yolov3_tf/models.py
yolov3_tf/utils.py
yolov3_tf-0.1.9.dist-info/LICENSE
yolov3_tf-0.1.9.dist-info/WHEEL
yolov3_tf-0.1.9.dist-info/METADATA
yolov3_tf-0.1.9.dist-info/RECORD
