Metadata-Version: 2.1
Name: yolov3-tf
Version: 0.1.9
Summary: YOLOv3 implementation in TensorFlow 2.x
Home-page: https://github.com/prp0x80/yolov3-tf
License: MIT
Keywords: yolo,yolov3,tensorflow
Author: Prashant Patel
Author-email: prashant.patel@kainos.com
Requires-Python: >=3.8,<3.11
Classifier: Environment :: GPU
Classifier: License :: OSI Approved :: MIT License
Classifier: Operating System :: OS Independent
Classifier: Programming Language :: Python :: 3
Classifier: Programming Language :: Python :: 3.10
Classifier: Programming Language :: Python :: 3.8
Classifier: Programming Language :: Python :: 3.9
Classifier: Topic :: Software Development :: Libraries :: Python Modules
Requires-Dist: Pillow (==9.1.1)
Requires-Dist: numpy (==1.22.4)
Requires-Dist: opencv-python (>=4.2.0,<5.0.0)
Requires-Dist: pandas (==1.4.2)
Project-URL: Repository, https://github.com/prp0x80/yolov3-tf
